sea_serpent-0.4.2.dist-info/licenses/LICENSE
seaserpent/__init__.py
seaserpent/admin.py
seaserpent/base.py
seaserpent/patch.py
seaserpent/utils.py
sea_serpent-0.4.2.dist-info/METADATA
sea_serpent-0.4.2.dist-info/WHEEL
sea_serpent-0.4.2.dist-info/top_level.txt
sea_serpent-0.4.2.dist-info/RECORD
