Metadata-Version: 2.4
Name: sea-serpent
Version: 0.4.2
Summary: Dataframe-like wrapper for SeaTable API.
Home-page: https://github.com/schlegelp/sea-serpent
Author: Philipp Schlegel
Author-email: pms70@cam.ac.uk
License: GNU GPL V3
Project-URL: Source, https://github.com/schlegelp/sea-serpent
Keywords: SeaTable API interface dataframe
Classifier: Development Status :: 5 - Production/Stable
Classifier: Intended Audience :: Science/Research
Classifier: Topic :: Scientific/Engineering :: Bio-Informatics
Classifier: License :: OSI Approved :: GNU General Public License v3 or later (GPLv3+)
Classifier: Programming Language :: Python :: 3
Classifier: Programming Language :: Python :: 3.6
Classifier: Programming Language :: Python :: 3.7
Classifier: Programming Language :: Python :: 3.8
Classifier: Programming Language :: Python :: 3.9
Requires-Python: >=3.6
License-File: LICENSE
Requires-Dist: pandas
Requires-Dist: seatable-api
Requires-Dist: numpy
Requires-Dist: tqdm
Requires-Dist: requests
Requires-Dist: PyJWT
Dynamic: author
Dynamic: author-email
Dynamic: classifier
Dynamic: description
Dynamic: description-content-type
Dynamic: home-page
Dynamic: keywords
Dynamic: license
Dynamic: license-file
Dynamic: project-url
Dynamic: requires-dist
Dynamic: requires-python
Dynamic: summary
